torndsession/__init__.py
torndsession/compat.py
torndsession/driver.py
torndsession/filesession.py
torndsession/memcachedsession.py
torndsession/memorysession.py
torndsession/redissession.py
torndsession/session.py
torndsession/sessionhandler.py
tornaSession-1.1.5.2.dist-info/LICENSE
tornaSession-1.1.5.2.dist-info/METADATA
tornaSession-1.1.5.2.dist-info/WHEEL
tornaSession-1.1.5.2.dist-info/top_level.txt
tornaSession-1.1.5.2.dist-info/zip-safe
tornaSession-1.1.5.2.dist-info/RECORD
